compute_wer/__init__.py
compute_wer/calculator.py
compute_wer/cli.py
compute_wer/utils.py
compute_wer/wer.py
compute_wer-0.2.3.dist-info/licenses/LICENSE
compute_wer-0.2.3.dist-info/METADATA
compute_wer-0.2.3.dist-info/WHEEL
compute_wer-0.2.3.dist-info/entry_points.txt
compute_wer-0.2.3.dist-info/top_level.txt
compute_wer-0.2.3.dist-info/RECORD
