Metadata-Version: 2.4
Name: compute-wer
Version: 0.2.3
Summary: Compute WER
Author-email: Zhendong Peng <pzd17@tsinghua.org.cn>
License-Expression: MIT
Project-URL: Homepage, https://github.com/pengzhendong/compute-wer
Project-URL: Documentation, https://github.com/pengzhendong/compute-wer#readme
Project-URL: BugTracker, https://github.com/pengzhendong/compute-wer/issues
Classifier: Programming Language :: Python :: 3
Classifier: Operating System :: OS Independent
Requires-Python: >=3.7
License-File: LICENSE
Requires-Dist: click
Requires-Dist: edit-distance
Dynamic: license-file
